Workbook

Sheet Instructions
A1: Kraig Ledger
A3: This spreadsheet is the primary database for the Kraig app. Google Apps Script (Code.gs, deployed as a web app) is the only thing that should write to it once it is live — editing a row by hand is fine any time, editing a formula is not.
A5: Tabs
A6: Accounts, Categories — reference data. Edit these rows directly, this is how you add a new account or category.
A7: Transactions, Transfers — the ledger. Written by the app through Apps Script. Columns shaded green (SignedAmount, Month on Transactions; Remaining, Progress on BudgetProgress) are formulas, pre-filled down thousands of rows — never type over them, and never use Insert > Row above the last used row, since that pushes data past the pre-filled range.
A8: BudgetRules — one row per recurring or one-off budget, this is the fix for the “budgets need repeat cycles” gap: Frequency, Interval, AnchorDate and EndCondition describe the cycle, Apps Script computes what a rule means for any given month on demand, no per-month row duplication needed.
A9: BudgetProgress — a read-only snapshot for eyeballing budgets directly in the sheet, regenerated on demand from the Kraig menu.
A10: Settings — key/value config. DefaultCurrency is the fixed anchor every exchange rate is relative to, do not change it casually. DisplayCurrency is the toggle: change it and every amount the app reads back (balances, transactions, budgets, dashboards) converts to it, nothing stored on this sheet is ever rewritten into a new currency.
A11: ExchangeRates — one row per currency, RateToBase = how many units of DefaultCurrency equal 1 unit of that currency. Add a row here before setting DisplayCurrency to a currency that isn't listed yet, or amounts in that currency will fail to convert.
A12: Lists — the dropdown source values used throughout. Add a value here to make it selectable elsewhere.
A14: Example transaction row
A15: Not written into the Transactions tab itself, since that would skew the account balance formulas away from your real starting balances. Shape to expect once the app is wired up:
... A20: Plain black text = a value you or Apps Script writes directly.

Sheet Lists
A1: AccountTypes | B1: TransactionTypes | C1: CategoryGroups | D1: Frequencies | E1: EndConditions | F1: TransferKinds | G1: Currencies
A2: Cash | B2: Expense | C2: Fixed | D2: Once | E2: Never | F2: Wallet to wallet | G2: XAF
A3: Savings Account | B3: Income | C3: Variable | D3: Weekly | E3: After Occurrences | F3: Wallet to savings | G3: XOF
A4: Debit Card | B4: Savings | C4: Recurring | D4: Monthly | E4: On Date | F4: Savings to wallet | G4: NGN
A5: Mobile Money | C5: One-Off | D5: Quarterly | G5: GHS
A6: E-wallet | C6: Debt | D6: Yearly | G6: USD
A7: Current Account | C7: Savings | G7: EUR
G8: GBP

Sheet Accounts
A1: ID | B1: Name | C1: Type | D1: Currency | E1: StartingBalance | F1: CurrentBalance | G1: Notes | H1: Archived
A2: acc_sgcb | B2: SGCB | C2: Current Account | D2: XAF | E2: 340000 | F2: =E2+SUMIF(Transactions!$F:$F,$A2,Transactions!$J:$J)+SUMIF(Transfers!$F:$F,$A2,Transfers!$G:$G)-SUMIF(Transfers!$E:$E,$A2,Transfers!$G:$G) | H2: =FALSE()
A3: acc_momo | B3: MOMO | C3: Mobile Money | D3: XAF | E3: 120000 | F3: =E3+SUMIF(Transactions!$F:$F,$A3,Transactions!$J:$J)+SUMIF(Transfers!$F:$F,$A3,Transfers!$G:$G)-SUMIF(Transfers!$E:$E,$A3,Transfers!$G:$G) | H3: =FALSE()
A4: acc_cash | B4: Cash | C4: Cash | D4: XAF | E4: 130000 | F4: =E4+SUMIF(Transactions!$F:$F,$A4,Transactions!$J:$J)+SUMIF(Transfers!$F:$F,$A4,Transfers!$G:$G)-SUMIF(Transfers!$E:$E,$A4,Transfers!$G:$G) | H4: =FALSE()
A5: acc_ecobank | B5: Ecobank | C5: Current Account | D5: XAF | E5: 940000 | F5: =E5+SUMIF(Transactions!$F:$F,$A5,Transactions!$J:$J)+SUMIF(Transfers!$F:$F,$A5,Transfers!$G:$G)-SUMIF(Transfers!$E:$E,$A5,Transfers!$G:$G) | H5: =FALSE()
A6: acc_om | B6: OM | C6: Mobile Money | D6: XAF | E6: 50000 | F6: =E6+SUMIF(Transactions!$F:$F,$A6,Transactions!$J:$J)+SUMIF(Transfers!$F:$F,$A6,Transfers!$G:$G)-SUMIF(Transfers!$E:$E,$A6,Transfers!$G:$G) | H6: =FALSE()
A7: acc_uba | B7: UBA | C7: Current Account | D7: XAF | E7: 90000 | F7: =E7+SUMIF(Transactions!$F:$F,$A7,Transactions!$J:$J)+SUMIF(Transfers!$F:$F,$A7,Transfers!$G:$G)-SUMIF(Transfers!$E:$E,$A7,Transfers!$G:$G) | H7: =FALSE()
A8: acc_napp | B8: NApp | C8: E-wallet | D8: XAF | E8: 13000 | F8: =E8+SUMIF(Transactions!$F:$F,$A8,Transactions!$J:$J)+SUMIF(Transfers!$F:$F,$A8,Transfers!$G:$G)-SUMIF(Transfers!$E:$E,$A8,Transfers!$G:$G) | H8: =FALSE()
F9: =E9+SUMIF(Transactions!$F:$F,$A9,Transactions!$J:$J)+SUMIF(Transfers!$F:$F,$A9,Transfers!$G:$G)-SUMIF(Transfers!$E:$E,$A9,Transfers!$G:$G)
F10: =E10+SUMIF(Transactions!$F:$F,$A10,Transactions!$J:$J)+SUMIF(Transfers!$F:$F,$A10,Transfers!$G:$G)-SUMIF(Transfers!$E:$E,$A10,Transfers!$G:$G)
F11: =E11+SUMIF(Transactions!$F:$F,$A11,Transactions!$J:$J)+SUMIF(Transfers!$F:$F,$A11,Transfers!$G:$G)-SUMIF(Transfers!$E:$E,$A11,Transfers!$G:$G)
F12: =E12+SUMIF(Transactions!$F:$F,$A12,Transactions!$J:$J)+SUMIF(Transfers!$F:$F,$A12,Transfers!$G:$G)-SUMIF(Transfers!$E:$E,$A12,Transfers!$G:$G)
F13: =E13+SUMIF(Transactions!$F:$F,$A13,Transactions!$J:$J)+SUMIF(Transfers!$F:$F,$A13,Transfers!$G:$G)-SUMIF(Transfers!$E:$E,$A13,Transfers!$G:$G)
F14: =E14+SUMIF(Transactions!$F:$F,$A14,Transactions!$J:$J)+SUMIF(Transfers!$F:$F,$A14,Transfers!$G:$G)-SUMIF(Transfers!$E:$E,$A14,Transfers!$G:$G)
F15: =E15+SUMIF(Transactions!$F:$F,$A15,Transactions!$J:$J)+SUMIF(Transfers!$F:$F,$A15,Transfers!$G:$G)-SUMIF(Transfers!$E:$E,$A15,Transfers!$G:$G)
F16: =E16+SUMIF(Transactions!$F:$F,$A16,Transactions!$J:$J)+SUMIF(Transfers!$F:$F,$A16,Transfers!$G:$G)-SUMIF(Transfers!$E:$E,$A16,Transfers!$G:$G)
F17: =E17+SUMIF(Transactions!$F:$F,$A17,Transactions!$J:$J)+SUMIF(Transfers!$F:$F,$A17,Transfers!$G:$G)-SUMIF(Transfers!$E:$E,$A17,Transfers!$G:$G)
F18: =E18+SUMIF(Transactions!$F:$F,$A18,Transactions!$J:$J)+SUMIF(Transfers!$F:$F,$A18,Transfers!$G:$G)-SUMIF(Transfers!$E:$E,$A18,Transfers!$G:$G)
F19: =E19+SUMIF(Transactions!$F:$F,$A19,Transactions!$J:$J)+SUMIF(Transfers!$F:$F,$A19,Transfers!$G:$G)-SUMIF(Transfers!$E:$E,$A19,Transfers!$G:$G)
F20: =E20+SUMIF(Transactions!$F:$F,$A20,Transactions!$J:$J)+SUMIF(Transfers!$F:$F,$A20,Transfers!$G:$G)-SUMIF(Transfers!$E:$E,$A20,Transfers!$G:$G)
... F200: =E200+SUMIF(Transactions!$F:$F,$A200,Transactions!$J:$J)+SUMIF(Transfers!$F:$F,$A200,Transfers!$G:$G)-SUMIF(Transfers!$E:$E,$A200,Transfers!$G:$G)

Sheet Categories
A1: ID | B1: Name | C1: TransactionType | D1: Group | E1: Notes | F1: Archived
A2: cat_subscriptions | B2: Subscriptions | C2: Expense | D2: Recurring | F2: =FALSE()
A3: cat_entertainments | B3: Entertainments | C3: Expense | D3: Variable | F3: =FALSE()
A4: cat_contributions | B4: Contributions | C4: Expense | D4: Recurring | F4: =FALSE()
A5: cat_medicare | B5: Medicare | C5: Expense | D5: Fixed | F5: =FALSE()
A6: cat_allowances | B6: Allowances | C6: Expense | D6: Fixed | F6: =FALSE()
A7: cat_renovations | B7: Renovations | C7: Expense | D7: One-Off | F7: =FALSE()
A8: cat_emergency | B8: Emergency | C8: Expense | D8: One-Off | F8: =FALSE()
A9: cat_unplanned | B9: Unplanned spending | C9: Expense | D9: One-Off | F9: =FALSE()
A10: cat_salary | B10: Salary | C10: Income | D10: Fixed | F10: =FALSE()
A11: cat_dsa | B11: DSA | C11: Income | D11: Variable | F11: =FALSE()
A12: cat_bonuses | B12: Bonuses | C12: Income | D12: One-Off | F12: =FALSE()
A13: cat_gift | B13: Gift | C13: Income | D13: One-Off | F13: =FALSE()
... A18: cat_general_savings | B18: General savings | C18: Savings | D18: Savings | F18: =FALSE()

Sheet Transactions
A1: ID | B1: ClientID | C1: Date | D1: Type | E1: Description | F1: AccountID | G1: CategoryID | H1: Amount | I1: Direction | J1: SignedAmount | K1: Month | L1: CreatedAt
J2: =IF(C2="","",IF(I2="Inflow",H2,-H2)) | K2: =IF(C2="","",TEXT(C2,"yyyy-mm"))
J3: =IF(C3="","",IF(I3="Inflow",H3,-H3)) | K3: =IF(C3="","",TEXT(C3,"yyyy-mm"))
J4: =IF(C4="","",IF(I4="Inflow",H4,-H4)) | K4: =IF(C4="","",TEXT(C4,"yyyy-mm"))
J5: =IF(C5="","",IF(I5="Inflow",H5,-H5)) | K5: =IF(C5="","",TEXT(C5,"yyyy-mm"))
J6: =IF(C6="","",IF(I6="Inflow",H6,-H6)) | K6: =IF(C6="","",TEXT(C6,"yyyy-mm"))
J7: =IF(C7="","",IF(I7="Inflow",H7,-H7)) | K7: =IF(C7="","",TEXT(C7,"yyyy-mm"))
J8: =IF(C8="","",IF(I8="Inflow",H8,-H8)) | K8: =IF(C8="","",TEXT(C8,"yyyy-mm"))
J9: =IF(C9="","",IF(I9="Inflow",H9,-H9)) | K9: =IF(C9="","",TEXT(C9,"yyyy-mm"))
J10: =IF(C10="","",IF(I10="Inflow",H10,-H10)) | K10: =IF(C10="","",TEXT(C10,"yyyy-mm"))
J11: =IF(C11="","",IF(I11="Inflow",H11,-H11)) | K11: =IF(C11="","",TEXT(C11,"yyyy-mm"))
J12: =IF(C12="","",IF(I12="Inflow",H12,-H12)) | K12: =IF(C12="","",TEXT(C12,"yyyy-mm"))
J13: =IF(C13="","",IF(I13="Inflow",H13,-H13)) | K13: =IF(C13="","",TEXT(C13,"yyyy-mm"))
... J5000: =IF(C5000="","",IF(I5000="Inflow",H5000,-H5000)) | K5000: =IF(C5000="","",TEXT(C5000,"yyyy-mm"))

Sheet Transfers
A1: ID | B1: ClientID | C1: Date | D1: Description | E1: FromAccountID | F1: ToAccountID | G1: Amount | H1: Kind | I1: Notes | J1: CreatedAt

Sheet BudgetRules
A1: ID | B1: CategoryID | C1: Description | D1: BudgetedAmount | E1: Frequency | F1: Interval | G1: AnchorDate | H1: EndCondition | I1: EndOccurrences | J1: EndDate | K1: AccountID | L1: Tag | M1: Archived
A2: rule_subscriptions | B2: cat_subscriptions | C2: Netflix, Spotify and other recurring app subscriptions | D2: 6000 | E2: Monthly | F2: 1 | G2: 2026-08-01 | H2: Never | M2: =FALSE()
A3: rule_entertainment | B3: cat_entertainments | C3: Movies, outings and fun activities | D3: 20000 | E3: Monthly | F3: 1 | G3: 2026-08-01 | H3: Never | M3: =FALSE()

Sheet BudgetProgress
A1: RuleID | B1: Category | C1: Description | D1: Budgeted | E1: Spent | F1: Remaining | G1: Progress | H1: LastRefreshed
F2: =IF(D2="","",D2-E2) | G2: =IF(OR(D2="",D2=0),"",E2/D2)
F3: =IF(D3="","",D3-E3) | G3: =IF(OR(D3="",D3=0),"",E3/D3)
F4: =IF(D4="","",D4-E4) | G4: =IF(OR(D4="",D4=0),"",E4/D4)
F5: =IF(D5="","",D5-E5) | G5: =IF(OR(D5="",D5=0),"",E5/D5)
F6: =IF(D6="","",D6-E6) | G6: =IF(OR(D6="",D6=0),"",E6/D6)
F7: =IF(D7="","",D7-E7) | G7: =IF(OR(D7="",D7=0),"",E7/D7)
F8: =IF(D8="","",D8-E8) | G8: =IF(OR(D8="",D8=0),"",E8/D8)
F9: =IF(D9="","",D9-E9) | G9: =IF(OR(D9="",D9=0),"",E9/D9)
F10: =IF(D10="","",D10-E10) | G10: =IF(OR(D10="",D10=0),"",E10/D10)
F11: =IF(D11="","",D11-E11) | G11: =IF(OR(D11="",D11=0),"",E11/D11)
F12: =IF(D12="","",D12-E12) | G12: =IF(OR(D12="",D12=0),"",E12/D12)
F13: =IF(D13="","",D13-E13) | G13: =IF(OR(D13="",D13=0),"",E13/D13)
... F200: =IF(D200="","",D200-E200) | G200: =IF(OR(D200="",D200=0),"",E200/D200)
A210: Regenerated by the “Kraig › Refresh Budget Progress” menu item (calls refreshBudgetProgress() in Code.gs). Not written to directly.

Sheet Settings
A1: Key | B1: Value
A2: TotalBudget | B2: 500000
A3: DefaultCurrency | B3: XAF
A4: DisplayCurrency | B4: XAF
A5: Timezone | B5: Africa/Douala
A6: HouseholdName | B6: Kraig

Sheet ExchangeRates
A1: Currency | B1: RateToBase | C1: UpdatedAt | D1: Notes
A2: XAF | B2: 1 | C2: 2026-08-29 | D2: Base currency (matches Settings!DefaultCurrency), always 1
A3: EUR | B3: 655.957 | C3: 2026-08-29 | D3: Fixed peg, CFA franc BEAC arrangement, does not change
A4: USD | B4: 566.19 | C4: 2026-08-29 | D4: Market rate (source: xe.com), update periodically
A5: GBP | B5: 766.429 | C5: 2026-08-29 | D5: Market rate (source: xe.com), update periodically
